miresi/__init__.py
miresi/client.py
miresi/config.py
miresi/interface.py
miresi/path.py
miresi-0.0.1.dist-info/METADATA
miresi-0.0.1.dist-info/WHEEL
miresi-0.0.1.dist-info/top_level.txt
miresi-0.0.1.dist-info/RECORD
