Metadata-Version: 2.1
Name: miresi
Version: 0.0.1
Summary: Miscellaneous Remote System Interface
Home-page: UNKNOWN
Author: SungHo Lee
Author-email: shlee@unc.edu
License: GNLv3
Keywords: Miscellaneous Remote System Interface
Platform: UNKNOWN
Classifier: Development Status :: 3 - Alpha
Classifier: Framework :: Jupyter
Classifier: Intended Audience :: Science/Research
Classifier: Topic :: Scientific/Engineering :: Information Analysis
Classifier: Natural Language :: English
Classifier: Programming Language :: Python :: 2.7
Classifier: Programming Language :: Python :: 3.7
Requires-Dist: ssh2-python
